r2analyze/__init__.py
r2analyze/analyze.py
r2analyze/pipe.py
r2analyze/r2.py
r2analyze-0.1.0.dist-info/LICENSE
r2analyze-0.1.0.dist-info/METADATA
r2analyze-0.1.0.dist-info/WHEEL
r2analyze-0.1.0.dist-info/entry_points.txt
r2analyze-0.1.0.dist-info/top_level.txt
r2analyze-0.1.0.dist-info/RECORD
