Metadata-Version: 2.1
Name: r2analyze
Version: 0.1.0
Summary: r2pipe script for Intezer Analyze
Home-page: https://github.com/
Author: Intezer
License: UNKNOWN
Platform: UNKNOWN
Classifier: Programming Language :: Python :: 3
Classifier: License :: OSI Approved :: BSD License
Classifier: Development Status :: 4 - Beta
Classifier: Operating System :: POSIX :: Linux
Classifier: Operating System :: Microsoft :: Windows
Classifier: Operating System :: MacOS :: MacOS X
License-File: LICENSE
Requires-Dist: r2pipe
Requires-Dist: requests
